praisonaiagents/__init__.py
praisonaiagents/__init__new.py
praisonaiagents/_config.py
praisonaiagents/_lazy.py
praisonaiagents/_logging.py
praisonaiagents/_resolver_helpers.py
praisonaiagents/_warning_patch.py
praisonaiagents/approval.py
praisonaiagents/flow_display.py
praisonaiagents/main.py
praisonaiagents/session.py
praisonaiagents/agent/__init__.py
praisonaiagents/agent/agent.py
praisonaiagents/agent/audio_agent.py
praisonaiagents/agent/autonomy.py
praisonaiagents/agent/code_agent.py
praisonaiagents/agent/context_agent.py
praisonaiagents/agent/deep_research_agent.py
praisonaiagents/agent/embedding_agent.py
praisonaiagents/agent/handoff.py
praisonaiagents/agent/image_agent.py
praisonaiagents/agent/message_queue.py
praisonaiagents/agent/ocr_agent.py
praisonaiagents/agent/prompt_expander_agent.py
praisonaiagents/agent/protocols.py
praisonaiagents/agent/query_rewriter_agent.py
praisonaiagents/agent/realtime_agent.py
praisonaiagents/agent/router_agent.py
praisonaiagents/agent/summarization.py
praisonaiagents/agent/video_agent.py
praisonaiagents/agent/vision_agent.py
praisonaiagents/agents/__init__.py
praisonaiagents/agents/agents.py
praisonaiagents/agents/auto_rag_agent.py
praisonaiagents/agents/autoagents.py
praisonaiagents/agents/delegator.py
praisonaiagents/agents/profiles.py
praisonaiagents/agents/protocols.py
praisonaiagents/app/__init__.py
praisonaiagents/app/config.py
praisonaiagents/app/protocols.py
praisonaiagents/background/__init__.py
praisonaiagents/background/config.py
praisonaiagents/background/job_manager.py
praisonaiagents/background/runner.py
praisonaiagents/background/task.py
praisonaiagents/bots/__init__.py
praisonaiagents/bots/config.py
praisonaiagents/bots/protocols.py
praisonaiagents/bus/__init__.py
praisonaiagents/bus/bus.py
praisonaiagents/bus/event.py
praisonaiagents/checkpoints/__init__.py
praisonaiagents/checkpoints/service.py
praisonaiagents/checkpoints/types.py
praisonaiagents/compaction/__init__.py
praisonaiagents-1.2.4.dist-info/METADATA
praisonaiagents-1.2.4.dist-info/WHEEL
praisonaiagents-1.2.4.dist-info/top_level.txt
praisonaiagents-1.2.4.dist-info/RECORD
